{
    "TradeActionProducer": 0,
    "QuoteJSF": 0,
    "ExternalContextProducer": 0,
    "QuoteData": 0,
    "JSFLoginFilter": 0,
    "PingCDIJSFBean": 0,
    "PingWebSocketJson": 0,
    "JsonDecoder": 0,
    "JsonEncoder": 0,
    "JsonMessage": 0,
    "PingServlet2Include": 0,
    "PingServlet2IncludeRcv": 0,
    "PingServlet2DB": 0,
    "TradeDirect": 0,
    "MarketSummarySingleton": 0,
    "PingJDBCRead": 0,
    "AccountDataBean": 0,
    "HoldingDataBean": 0,
    "PingJDBCWrite": 0,
    "QuoteDataBean": 0,
    "OrderDataBean": 0,
    "AccountProfileDataBean": 0,
    "PingJDBCRead2JSP": 0,
    "KeyBlock": 0,
    "KeySequenceDirect": 0,
    "KeyBlock::KeyBlockIterator": 0,
    "RecentStockChangeList": 0,
    "DTStreamer3MDB": 0,
    "MarketSummaryWebSocket": 0,
    "TradeAction": 0,
    "TradeSLSBBean": 0,
    "PingServlet2SessionLocal": 0,
    "TradeScenarioServlet": 0,
    "OrdersAlertFilter": 0,
    "TradeAppServlet": 0,
    "TradeServletAction": 0,
    "FinancialUtils": 0,
    "MDBStats": 0,
    "TimerStat": 0,
    "PingBean": 1,
    "PingServlet2PDF": 1,
    "PingServlet2Jsp": 1,
    "PingServlet2Servlet": 1,
    "PingServlet2ServletRcv": 1,
    "TradeWebContextListener": 1,
    "PingUpgradeServlet": 1,
    "TradeConfig": 1,
    "TradeBuildDB": 1,
    "Log": 1,
    "RunStatsDataBean": 1,
    "MarketSummaryDataBean": 1,
    "TradeConfigServlet": 1,
    "PingCDIBean": 2,
    "PingServletCDIBeanManagerViaJNDI": 2,
    "PingServletCDIBeanManagerViaCDICurrent": 2,
    "PingInterceptor": 2,
    "PingEJBLocalDecorator": 2,
    "PingServletCDI": 2,
    "PingEJBLocal": 2,
    "ActionDecoder": 2,
    "ActionMessage": 2
}