{
    "Root--ImageServlet": 67,
    "ImageServlet--ImageServlet": 66,
    "ImageServlet--Util": 66,
    "ImageServlet--CatalogMgr": 66,
    "CatalogMgr--CatalogMgr": 109,
    "CatalogMgr--Inventory": 268,
    "Root--AccountBean": 647,
    "AccountBean--AccountBean": 163,
    "Root--ShoppingBean": 361,
    "Root--ShoppingCartBean": 215,
    "ShoppingCartBean--ShoppingCartBean": 190,
    "Root--LoginInfo": 20,
    "Root--ShoppingItem": 96,
    "ShoppingItem--Inventory": 108,
    "ShoppingBean--ShoppingCartBean": 21,
    "ShoppingCartBean--Inventory": 95,
    "ShoppingBean--ShoppingBean": 15,
    "ShoppingBean--ShoppingItem": 11,
    "ShoppingItem--ShoppingItem": 24,
    "Root--OrderInfo": 233,
    "OrderInfo--OrderInfo": 12,
    "OrderInfo--Util": 12,
    "AccountBean--OrderInfo": 75,
    "AccountBean--Util": 6,
    "AccountBean--ShoppingBean": 3,
    "Root--Customer": 56,
    "AccountBean--Customer": 45,
    "AccountBean--CustomerMgr": 4,
    "AccountBean--ShoppingCartBean": 9,
    "ShoppingCartBean--Util": 3,
    "Util--Util": 59,
    "ShoppingCartBean--OrderItem": 16,
    "OrderItem--Inventory": 28,
    "OrderItem--Util": 4,
    "OrderItem--OrderItem": 4,
    "ShoppingCartBean--Order": 3,
    "Order--Order": 81,
    "Order--OrderItem": 16,
    "OrderItem--Order": 12,
    "OrderItem--OrderItem::PK": 4,
    "OrderItem::PK--Util": 10,
    "OrderInfo--Order": 48,
    "AccountBean--MailerBean": 3,
    "MailerBean--MailerBean": 6,
    "MailerBean--Util": 15,
    "MailerBean--Order": 21,
    "MailerBean--Customer": 3,
    "MailerBean--EMailMessage": 30,
    "AccountBean--MailerAppException": 3,
    "ShoppingBean--CatalogMgr": 9,
    "CatalogMgr--Util": 48,
    "ShoppingBean--ProductBean": 56,
    "Root--ProductBean": 445,
    "ProductBean--Inventory": 16,
    "ProductBean--Util": 11,
    "Root--Inventory": 416,
    "AccountBean--LoginInfo": 10,
    "Root--PopulateDBBean": 1,
    "PopulateDBBean--Util": 1,
    "PopulateDBBean--ResetDBBean": 1,
    "ResetDBBean--Util": 756,
    "Util--ListProperties": 6,
    "ListProperties--Util": 158,
    "ListProperties--ListProperties": 48,
    "ResetDBBean--Inventory": 43,
    "Inventory--Inventory": 749,
    "Inventory--Util": 43,
    "ResetDBBean--CatalogMgr": 86,
    "CatalogMgr--Supplier": 1,
    "CatalogMgr--Order": 2,
    "CatalogMgr--Customer": 1,
    "CatalogMgr--OrderItem": 2,
    "CatalogMgr--BackOrder": 1,
    "CatalogMgr--OrderItem::PK": 2,
    "ResetDBBean--ResetDBBean": 43,
    "ResetDBBean--CustomerMgr": 1,
    "CustomerMgr--Customer": 3,
    "Customer--Customer": 31,
    "Util--SuppliersBean": 1,
    "SuppliersBean--Util": 3,
    "SuppliersBean--Supplier": 1,
    "Supplier--Supplier": 8,
    "ShoppingBean--Inventory": 51,
    "Root--HelpBean": 2,
    "HelpBean--Util": 1
}