{
  "OrderDataBean": 1,
  "PingServletWriter": 9,
  "PingCDIBean": 14,
  "MarketSummarySingleton": 14,
  "PingServlet2SessionLocal": 14,
  "JsonEncoder": 13,
  "TimerStat": 12,
  "AccountProfileDataBean": 1,
  "PingServlet2Servlet": 3,
  "PingSession2": 14,
  "TradeBuildDB": 14,
  "PingSession3": 14,
  "PingSession1": 14,
  "TradeScenarioServlet": 7,
  "KeyBlock": 12,
  "MarketSummaryWebSocket": 14,
  "PingInterceptor": 14,
  "PingServlet2PDF": 14,
  "TradeAction": 7,
  "ActionMessage": 11,
  "TradeActionProducer": 7,
  "PingServletCDIBeanManagerViaJNDI": 4,
  "PingWebSocketTextSync": 2,
  "MDBStats": 14,
  "AccountDataBean": 1,
  "QuoteData": 10,
  "Log": 14,
  "MarketSummaryDataBean": 14,
  "TradeServletAction": 10,
  "PingBean": 14,
  "PingServlet2Jsp": 3,
  "QuoteJSF": 14,
  "DTStreamer3MDB": 14,
  "JsonDecoder": 14,
  "TradeDirect": 14,
  "PingJDBCWrite": 14,
  "TradeConfig": 14,
  "PingWebSocketJson": 13,
  "PingJSONP": 11,
  "TradeWebContextListener": 14,
  "TradeConfigServlet": 14,
  "JSFLoginFilter": 0,
  "ActionDecoder": 14,
  "KeyBlock::KeyBlockIterator": 14,
  "PingManagedThread": 5,
  "PingServlet2ServletRcv": 4,
  "PingServlet": 14,
  "KeySequenceDirect": 14,
  "ExternalContextProducer": 14,
  "TradeSLSBBean": 1,
  "PingServletCDIBeanManagerViaCDICurrent": 14,
  "TradeAppServlet": 7,
  "PingWebSocketBinary": 14,
  "PingServlet2DB": 8,
  "HoldingDataBean": 1,
  "PingEJBLocalDecorator": 6,
  "PingUpgradeServlet": 14,
  "PingServlet2JNDI": 8,
  "PingCDIJSFBean": 14,
  "PingJDBCRead": 14,
  "OrdersAlertFilter": 0,
  "PingManagedExecutor": 5,
  "FinancialUtils": 10,
  "PingServlet2IncludeRcv": 14,
  "ExplicitGC": 14,
  "PingWebSocketTextAsync": 2,
  "PingJDBCRead2JSP": 14,
  "RunStatsDataBean": 14,
  "PingEJBLocal": 6,
  "RecentStockChangeList": 14,
  "JsonMessage": 13,
  "PingServlet2Include": 9,
  "QuoteDataBean": 14,
  "PingServletCDI": 6
}